{
    "##": "TODO: Use proper arm64 binaries when available",
    "version": "1.30.2",
    "description": "Command-line interface for Hetzner Cloud",
    "homepage": "https://github.com/hetznercloud/cli",
    "license": {
        "identifier": "MIT",
        "url": "https://github.com/hetznercloud/cli/blob/master/LICENSE"
    },
    "changelog": "https://github.com/hetznercloud/cli/releases/v1.30.2",
    "architecture": {
        "64bit": {
            "url": "https://github.com/hetznercloud/cli/releases/download/v1.30.2/hcloud-windows-amd64.zip",
            "hash": "53f5e36053f353374bb9c1a7b04492e74de63c63e8b2fad5522abdc1907135ec"
        },
        "32bit": {
            "url": "https://github.com/hetznercloud/cli/releases/download/v1.30.2/hcloud-windows-386.zip",
            "hash": "eb7a73ddce9d713e8579b50f9ec5fb508064308718868fb53fc9df515e928a0d"
        },
        "arm64": {
            "url": "https://github.com/hetznercloud/cli/releases/download/v1.30.2/hcloud-windows-armv7.zip",
            "hash": "f1b13cccdc3f19203ff92cbf444ac32e31c8b3e16c49ab726193b41c3c3074ed"
        }
    },
    "bin": "hcloud.exe",
    "checkver": "github",
    "autoupdate": {
        "changelog": "https://github.com/hetznercloud/cli/releases/v$version",
        "architecture": {
            "64bit": {
                "url": "https://github.com/hetznercloud/cli/releases/download/v$version/hcloud-windows-amd64.zip"
            },
            "32bit": {
                "url": "https://github.com/hetznercloud/cli/releases/download/v$version/hcloud-windows-386.zip"
            },
            "arm64": {
                "url": "https://github.com/hetznercloud/cli/releases/download/v$version/hcloud-windows-armv7.zip"
            }
        },
        "hash": {
            "url": "$baseurl/checksums.txt"
        }
    }
}
